pretty_loguru/__init__.py
pretty_loguru/advanced/__init__.py
pretty_loguru/advanced/helpers.py
pretty_loguru/core/__init__.py
pretty_loguru/core/base.py
pretty_loguru/core/cleaner.py
pretty_loguru/core/config.py
pretty_loguru/core/event_system.py
pretty_loguru/core/extension_system.py
pretty_loguru/core/handlers.py
pretty_loguru/core/presets.py
pretty_loguru/core/registry.py
pretty_loguru/core/target_formatter.py
pretty_loguru/core/templates.py
pretty_loguru/factory/__init__.py
pretty_loguru/factory/creator.py
pretty_loguru/factory/methods.py
pretty_loguru/factory/updater.py
pretty_loguru/formats/__init__.py
pretty_loguru/formats/ascii_art.py
pretty_loguru/formats/block.py
pretty_loguru/formats/figlet.py
pretty_loguru/formats/rich_components.py
pretty_loguru/integrations/__init__.py
pretty_loguru/integrations/fastapi.py
pretty_loguru/integrations/uvicorn.py
pretty_loguru/types/__init__.py
pretty_loguru/types/protocols.py
pretty_loguru/utils/__init__.py
pretty_loguru/utils/dependencies.py
pretty_loguru/utils/validators.py
pretty_loguru-1.2.0.dist-info/licenses/LICENSE
pretty_loguru-1.2.0.dist-info/METADATA
pretty_loguru-1.2.0.dist-info/WHEEL
pretty_loguru-1.2.0.dist-info/top_level.txt
pretty_loguru-1.2.0.dist-info/RECORD
