Metadata-Version: 2.4
Name: pretty-loguru
Version: 1.2.0
Summary: A Loguru-based logger with Rich panels, ASCII art headers, blocks and more.
Author-email: JonesHong <latte831104@gmail.com>
License: MIT License
Project-URL: Source, https://github.com/JonesHong/pretty-loguru
Project-URL: Tracker, https://github.com/JonesHong/pretty-loguru/issues
Classifier: Programming Language :: Python :: 3
Classifier: Operating System :: OS Independent
License-File: LICENSE
Requires-Dist: loguru>=0.6.0
Requires-Dist: rich>=12.0.0
Requires-Dist: art>=5.0.0
Requires-Dist: pyfiglet>=1.0.1
Requires-Dist: matplotlib>=3.7.0
Requires-Dist: python-dateutil>=2.8.2
Dynamic: license-file
